{
  "timestamp": "2025-11-25T21:18:58.692Z",
  "blockNumber": 23878426,
  "riskLevel": "low",
  "riskPercentage": 0,
  "metrics": {
    "largestDisputeBond": 0,
    "forkThresholdPercent": 0,
    "activeDisputes": 0,
    "disputeDetails": []
  },
  "nextUpdate": "2025-11-25T22:20:17.094Z",
  "rpcInfo": {
    "endpoint": "https://eth.llamarpc.com",
    "latency": 268,
    "fallbacksAttempted": 0
  },
  "calculation": {
    "method": "GitHub Actions + Public RPC",
    "forkThreshold": 275000
  }
}