{
  "timestamp": "2025-12-14T17:17:21.263Z",
  "blockNumber": 24012281,
  "riskLevel": "low",
  "riskPercentage": 0,
  "metrics": {
    "largestDisputeBond": 0,
    "forkThresholdPercent": 0,
    "activeDisputes": 0,
    "disputeDetails": []
  },
  "nextUpdate": "2025-12-14T18:17:34.339Z",
  "rpcInfo": {
    "endpoint": "https://eth.llamarpc.com",
    "latency": 241,
    "fallbacksAttempted": 0
  },
  "calculation": {
    "method": "GitHub Actions + Public RPC",
    "forkThreshold": 275000
  }
}