{
  "timestamp": "2025-09-29T22:16:15.494Z",
  "blockNumber": 23471572,
  "riskLevel": "low",
  "riskPercentage": 0,
  "metrics": {
    "largestDisputeBond": 0,
    "forkThresholdPercent": 0,
    "activeDisputes": 0,
    "disputeDetails": []
  },
  "nextUpdate": "2025-09-29T23:16:53.843Z",
  "rpcInfo": {
    "endpoint": "https://eth.llamarpc.com",
    "latency": 243,
    "fallbacksAttempted": 0
  },
  "calculation": {
    "method": "GitHub Actions + Public RPC",
    "forkThreshold": 275000
  }
}