{
  "timestamp": "2025-09-30T09:20:38.285Z",
  "blockNumber": 23474876,
  "riskLevel": "low",
  "riskPercentage": 0,
  "metrics": {
    "largestDisputeBond": 0,
    "forkThresholdPercent": 0,
    "activeDisputes": 0,
    "disputeDetails": []
  },
  "nextUpdate": "2025-09-30T10:21:10.100Z",
  "rpcInfo": {
    "endpoint": "https://eth.llamarpc.com",
    "latency": 204,
    "fallbacksAttempted": 0
  },
  "calculation": {
    "method": "GitHub Actions + Public RPC",
    "forkThreshold": 275000
  }
}